{
	"partitions" : [
		{
			"name" : "Top",
			"pins" : [
				{
					"name" : "col[0]",
					"strict" : false
				},
				{
					"name" : "col[1]",
					"strict" : false
				},
				{
					"name" : "col[2]",
					"strict" : false
				},
				{
					"name" : "col[3]",
					"strict" : false
				},
				{
					"name" : "VGA_Hsync_n",
					"strict" : false
				},
				{
					"name" : "VGA_Vsync_n",
					"strict" : false
				},
				{
					"name" : "VGA_R",
					"strict" : false
				},
				{
					"name" : "VGA_G",
					"strict" : false
				},
				{
					"name" : "VGA_B",
					"strict" : false
				},
				{
					"name" : "salidaPWM",
					"strict" : false
				},
				{
					"name" : "rst",
					"strict" : false
				},
				{
					"name" : "clk",
					"strict" : false
				},
				{
					"name" : "fila[0]",
					"strict" : false
				},
				{
					"name" : "fila[1]",
					"strict" : false
				},
				{
					"name" : "fila[2]",
					"strict" : false
				},
				{
					"name" : "fila[3]",
					"strict" : false
				}
			]
		}
	]
}